[
    {
        "center" : [0,0],
        "zoom" : 1,
        "marker" : [26.8854476,75.6501289]
    },
    {
        "center" : [31.262230, 49.159345],
        "zoom" : 2,
        "marker" : [26.8854476,75.6501289]
    },
    {
        "center" : [27.588749, 78.514814],
        "zoom" : 3,
        "marker" : [26.8854476,75.6501289]
    },
    {
        "center" : [27.777864, 77.503440],
        "zoom" : 5,
        "marker" : [26.8854476,75.6501289]
    },
    {
        "center" : [26.921793, 75.775931],
        "zoom" : 12,
        "marker" : [26.904245, 75.783240]
    }
]