[
    {
        "center" : [0,0],
        "zoom" : 1,
        "marker" : [48.1550543,11.4014091]
    },
    {
        "center" : [38.001864, -25.318565],
        "zoom" : 2,
        "marker" : [48.1550543,11.4014091]
    },
    {
        "center" : [48.066883, 4.503464],
        "zoom" : 3,
        "marker" : [48.1550543,11.4014091]
    },
    {
        "center" : [48.2491147,11.5304171],
        "zoom" : 6,
        "marker" : [48.1550543,11.4014091]
    },
    {
        "center" : [48.140267, 11.573230],
        "zoom" : 9,
        "marker" : [48.140267, 11.573230]
    }
]